blade_bench/__init__.py
blade_bench/baselines/__init__.py
blade_bench/baselines/agent/__init__.py
blade_bench/baselines/agent/examples/__init__.py
blade_bench/baselines/agent/examples/react_example.py
blade_bench/baselines/agent/react_agent.py
blade_bench/baselines/config.py
blade_bench/baselines/lm/__init__.py
blade_bench/baselines/lm/format.py
blade_bench/baselines/lm/gen_analysis.py
blade_bench/baselines/lm/mcq.py
blade_bench/baselines/multirun.py
blade_bench/baselines/run.py
blade_bench/baselines/run_mcq.py
blade_bench/conf/llm_config.yml
blade_bench/config.py
blade_bench/data/__init__.py
blade_bench/data/annotation.py
blade_bench/data/datamodel/__init__.py
blade_bench/data/datamodel/graph.py
blade_bench/data/datamodel/mcq.py
blade_bench/data/datamodel/specs.py
blade_bench/data/datamodel/transform_graph.py
blade_bench/data/datamodel/transform_state.py
blade_bench/data/datamodel/transforms.py
blade_bench/data/datamodel/verbs.py
blade_bench/data/dataset.py
blade_bench/data/load_annotation.py
blade_bench/data/process/__init__.py
blade_bench/data/process/load.py
blade_bench/data/process/transforms/__init__.py
blade_bench/data/process/transforms/dataflow.py
blade_bench/data/process/transforms/expand_graph.py
blade_bench/data/process/transforms/graph_paths.py
blade_bench/data/process/transforms/parser/__init__.py
blade_bench/data/process/transforms/parser/base.py
blade_bench/data/process/transforms/parser/condition.py
blade_bench/datasets/affairs/annotations.csv
blade_bench/datasets/affairs/data.csv
blade_bench/datasets/affairs/info.json
blade_bench/datasets/affairs/mcq_dataset.json
blade_bench/datasets/amtl/annotations.csv
blade_bench/datasets/amtl/data.csv
blade_bench/datasets/amtl/info.json
blade_bench/datasets/amtl/mcq_dataset.json
blade_bench/datasets/boxes/annotations.csv
blade_bench/datasets/boxes/data.csv
blade_bench/datasets/boxes/info.json
blade_bench/datasets/boxes/mcq_dataset.json
blade_bench/datasets/caschools/annotations.csv
blade_bench-0.1.1.dist-info/METADATA
blade_bench-0.1.1.dist-info/WHEEL
blade_bench-0.1.1.dist-info/RECORD
