Metadata-Version: 2.1
Name: blade-bench
Version: 0.1.1
Summary: Dataset and code for 'BLADE: Benchmarking Language Model Agents for Data-Driven Science'(https://arxiv.org/abs/2408.09667)
Home-page: https://github.com/behavioral-data/BLADE
Author: Ken Gu
Author-email: kenqgu@cs.washington.edu
Requires-Python: >=3.10,<4.0
Classifier: Programming Language :: Python :: 3
Classifier: Programming Language :: Python :: 3.10
Classifier: Programming Language :: Python :: 3.11
Classifier: Programming Language :: Python :: 3.12
Requires-Dist: absl-py (>=2.1.0,<3.0.0)
Requires-Dist: accelerate (>=0.31.0,<0.32.0)
Requires-Dist: anthropic (>=0.29.0,<0.30.0)
Requires-Dist: astor (>=0.8.1,<0.9.0)
Requires-Dist: backoff (>=2.2.1,<3.0.0)
Requires-Dist: click (>=8.1.7,<9.0.0)
Requires-Dist: diskcache (>=5.6.3,<6.0.0)
Requires-Dist: fastapi (>=0.111.0,<0.112.0)
Requires-Dist: google-generativeai (>=0.7.0,<0.8.0)
Requires-Dist: groq (>=0.9.0,<0.10.0)
Requires-Dist: ipykernel (>=6.29.4,<7.0.0)
Requires-Dist: ipython (>=8.25.0,<9.0.0)
Requires-Dist: langchain (>=0.2.5,<0.3.0)
Requires-Dist: loguru (>=0.7.2,<0.8.0)
Requires-Dist: matplotlib (>=3.9.0,<4.0.0)
Requires-Dist: mistralai (>=0.4.2,<0.5.0)
Requires-Dist: nbclient (>=0.10.0,<0.11.0)
Requires-Dist: nbformat (>=5.10.4,<6.0.0)
Requires-Dist: networkx (>=3.3,<4.0)
Requires-Dist: openai (>=1.35.3,<2.0.0)
Requires-Dist: pandas (==1.5.3)
Requires-Dist: pillow (>=10.3.0,<11.0.0)
Requires-Dist: pydantic (>=2.7.4,<3.0.0)
Requires-Dist: python-dotenv (>=1.0.1,<2.0.0)
Requires-Dist: rich (>=13.7.1,<14.0.0)
Requires-Dist: scikit-learn (>=1.5.0,<2.0.0)
Requires-Dist: scipy (>=1.13.1,<2.0.0)
Requires-Dist: seaborn (>=0.13.2,<0.14.0)
Requires-Dist: statsmodels (>=0.14.2,<0.15.0)
Requires-Dist: tiktoken (>=0.7.0,<0.8.0)
Requires-Dist: together (>=1.2.3,<2.0.0)
Requires-Dist: transformers (>=4.41.2,<5.0.0)
Project-URL: Repository, https://github.com/behavioral-data/BLADE
